tradeset/__init__.py
tradeset/tools.py
tradeset-0.0.8.dist-info/LICENSE
tradeset-0.0.8.dist-info/METADATA
tradeset-0.0.8.dist-info/WHEEL
tradeset-0.0.8.dist-info/top_level.txt
tradeset-0.0.8.dist-info/RECORD
