Metadata-Version: 2.1
Name: tradeset
Version: 0.0.8
Summary: Tradeset
Author-email: Mohammad Talaei <m.talaei.sut@gmail.com>, Morteza Omidi <mortezaomidi24@yahoo.com>
Project-URL: Homepage, https://tradeset.ai/
Project-URL: Documents, https://docs.tradeset.ai/
Project-URL: Issues, https://github.com/tradeset/tradeset-public/issues/
Project-URL: Source, https://github.com/tradeset/tradeset-public/
Classifier: Programming Language :: Python :: 3
Classifier: License :: OSI Approved :: MIT License
Classifier: Operating System :: OS Independent
Requires-Python: >=3.8
License-File: LICENSE
Requires-Dist: pandas
Requires-Dist: scikit-learn
Requires-Dist: numpy
Requires-Dist: requests
